setup.py
wifiinfo/Connection.py
wifiinfo/__init__.py
wifiinfo.egg-info/PKG-INFO
wifiinfo.egg-info/SOURCES.txt
wifiinfo.egg-info/dependency_links.txt
wifiinfo.egg-info/not-zip-safe
wifiinfo.egg-info/top_level.txt