Metadata-Version: 1.0
Name: wifiinfo
Version: 0.1
Summary: Get your current wifi information with Python
Home-page: https://github.com/keithweaver/wifiinfo
Author: keithweaver
Author-email: me@keithweaver.ca
License: Apache License 2.0
Platform: UNKNOWN
